{
    "fe": {
        "category": "Front end",
        "skills": {
            "HTML": "8",
            "CSS/SASS": "7",
            "React": "8",
            "VanillaJS": "7",
            "Socket.io": "6"
        }
    },
    "be": {
        "category": "Back end",
        "skills": {
            "GOlang": "7",
            "Python": "6",
            "Node.js": "5",
            "SQL/PosgreSQL": "5",
            "MongoDB": "7"
        }
    },
    "data": {
        "category": "Data manipulation",
        "skills": {
            "Excel": "8",
            "SQL": "6",
            "Python": "6",
            "PowerBI": "3",
            "Tableau": "2"
        }
    },
    "visual": {
        "category": "Visual art tools",
        "skills": {
            "Adobe Premiere Pro": "8",
            "Adobe Photoshop": "5",
            "Adobe Illustrator": "4",
            "Blender": "5",
            "Adobe After Effects": "3"
        }
    }
}
